pubmed_bibtex/__init__.py
pubmed_bibtex/__main__.py
pubmed_bibtex/version.py
pubmed_bibtex-1.0.0.dist-info/COPYING
pubmed_bibtex-1.0.0.dist-info/METADATA
pubmed_bibtex-1.0.0.dist-info/WHEEL
pubmed_bibtex-1.0.0.dist-info/entry_points.txt
pubmed_bibtex-1.0.0.dist-info/top_level.txt
pubmed_bibtex-1.0.0.dist-info/RECORD
