Metadata-Version: 2.1
Name: pubmed-bibtex
Version: 1.0.0
Summary: Generate BibTeX Entries for PubMed Publications
Home-page: https://github.com/fphammerle/pubmed-bibtex
Author: Fabian Peter Hammerle
Author-email: fabian@hammerle.me
License: GPLv3+
Keywords: article,bibtex,citation,journal,latex,publication,pubmed,reference,research,tex,texmed
Platform: UNKNOWN
Classifier: Development Status :: 4 - Beta
Classifier: Intended Audience :: Healthcare Industry
Classifier: Intended Audience :: Science/Research
Classifier: License :: OSI Approved :: GNU General Public License v3 or later (GPLv3+)
Classifier: Programming Language :: Python :: 3.7
Classifier: Programming Language :: Python :: 3.8
Classifier: Programming Language :: Python :: 3.9
Classifier: Programming Language :: Python :: 3.10
Classifier: Topic :: Scientific/Engineering :: Medical Science Apps.
Classifier: Topic :: Utilities
Requires-Python: >=3.7
